{
  "Natural History": [
    "Sweet Bark"
  ], 
  "details": "Acts on the digestive tract; constipation. Aversion to smell of tobacco. INCLINATION TO VOMIT very marked.", 
  "symptoms": {
    "Rectum": [
      "Constipation; stools hard, covered with mucus", 
      "Bright blood with stool", 
      "Diarrhoea alternating with hard, lumpy stool, with backache and lassitude, preceded by griping", 
      "Gnawing pain high up in rectum"
    ], 
    "Stomach": [
      "Hunger after meals", 
      "Desire for hot drinks", 
      "NAUSEA AND VOMITING", 
      "Pain in stomach as from a shock", 
      "Pressing colic"
    ]
  }, 
  "name": "Cascarilla", 
  "dosage": "First to third potency."
}